{
  "generator-jhipster": {
    "applicationType": "microservice",
    "authenticationType": "jwt",
    "baseName": "msorders",
    "blueprints": [],
    "buildTool": "maven",
    "cacheProvider": "no",
    "creationTimestamp": 1645791831764,
    "databaseType": "sql",
    "devDatabaseType": "mssql",
    "dtoSuffix": "DTO",
    "enableGradleEnterprise": false,
    "enableHibernateCache": false,
    "enableSwaggerCodegen": true,
    "enableTranslation": true,
    "entitySuffix": "",
    "jhiPrefix": "jhi",
    "jhipsterVersion": "7.6.0",
    "jwtSecretKey": "ZmFjZDUyZTk3NTRjYzRlZGRkMzQyYzY4OGU2NzhhMDQ5MGI2NzljMDk5ZDY1Y2VkNTJjZTlhNWNhZmM5ZjJkOTUzNWJiNDc3Y2UxNzA0MGJhOTNiMDYzNDVmNDY5OWVlMDk0NzE4ZjVmYmNlOGQzNWY0NjBmMTc4YjRiZTYwN2Y=",
    "languages": ["en"],
    "messageBroker": "kafka",
    "monorepository": true,
    "nativeLanguage": "en",
    "otherModules": [],
    "packageName": "com.ecommerce.msorders",
    "pages": [],
    "prodDatabaseType": "mssql",
    "reactive": true,
    "searchEngine": false,
    "serverPort": "9990",
    "serverSideOptions": ["messageBroker:kafka", "enableSwaggerCodegen:true"],
    "serviceDiscoveryType": "eureka",
    "skipCheckLengthOfIdentifier": false,
    "skipClient": true,
    "skipCommitHook": true,
    "skipFakeData": false,
    "skipUserManagement": true,
    "testFrameworks": ["cypress"],
    "websocket": false,
    "withAdminUi": false
  }
}
